setup.py
tiny/__init__.py
tiny/app.py
tiny/tiny.py
tiny.egg-info/PKG-INFO
tiny.egg-info/SOURCES.txt
tiny.egg-info/dependency_links.txt
tiny.egg-info/not-zip-safe
tiny.egg-info/top_level.txt