Metadata-Version: 1.0
Name: tiny
Version: 0.1.3
Summary: A small web framework for learning about web frameworks.
Home-page: https://github.com/jimjshields/tiny
Author: Jim Shields
Author-email: jim.j.shields@gmail.com
License: MIT
Platform: UNKNOWN
